<?xml version="1.0" encoding="UTF-8"?>
<questions>
	<question ID="1">
		Mikä seuraavista valtioista on rakennettu osittain täyttömaalle?
	</question>
	<question ID="2">
		Milloin Google on perustettu?
	</question>	
	<question ID="3">
		Kuka on Miss Suomi 2015?
	</question>	
	<question ID="4">
		Mikä yhtye tai artisti ei ole Rock and Roll Hall of Famessä?
	</question>	
	<question ID="5">
		Mikä on kaikkien aikojen tuottavin elokuva?
	</question>	
	<question ID="6">
		Kuka oli Suomen ensimmäinen Presidentti?
	</question>	
	<question ID="7">
		Mikä oli ensimmäinen pelikonsoli?
	</question>	
	<question ID="8">
		Kuka tai mikä kaikkien aikojen myydyin artisti tai yhtye? 
	</question>	
	<question ID="9">
		Mikä on Australian pääkaupunki?
	</question>	
	<question ID="10">
		Minkä värinen on punainen vasara pimeässä huoneessa?
	</question>	
	<question ID="11">
		Kaikkien aikojen myydyin videopeli (kappalemäärällisesti)?
	</question>
	<question ID="12">
		Kuka oli Yhdysvaltojen kolmas presidentti?
	</question>	
	<question ID="13">
		Milloin Microsoft on perustettu?
	</question>	
	<question ID="14">
		Mikä on Andorran pääkaupunki?
	</question>	
	<question ID="15">
		Mikä seuraavista ei ole Joulupukin poron nimi?
	</question>	
	<question ID="16">
		Mikä on maailman korkein vuori?
	</question>	
	<question ID="17">
		Mikä on maailman korkein rakennus?
	</question>	
	<question ID="18">
		Mikä on Maailman kaikkien aikojen myydyin kirja?
	</question>	
	<question ID="19">
		Mikä on Suomen kaikkienaikojen katsotuin elokuva?
	</question>	
	<question ID="20">
		Mikä ei ole planeetta?
	</question>		
</questions>